pypolyback/__init__.py
pypolyback/apiobject.py
pypolyback/commandline.py
pypolyback/config.py
pypolyback/log.py
pypolyback/project.py
pypolyback/routes.py
pypolyback/server.py
pypolyback-0.12.7.dist-info/DESCRIPTION.rst
pypolyback-0.12.7.dist-info/METADATA
pypolyback-0.12.7.dist-info/RECORD
pypolyback-0.12.7.dist-info/WHEEL
pypolyback-0.12.7.dist-info/entry_points.txt
pypolyback-0.12.7.dist-info/metadata.json
pypolyback-0.12.7.dist-info/top_level.txt
