Metadata-Version: 2.0
Name: pypolyback
Version: 0.12.7
Summary: A simple back-end rest framework in python using twisted and cyclone
Home-page: https://github.com/seijihirao/pypolyback
Author: Rodrigo Seiji Piubeli Hirao
Author-email: rodrigo.seiji.hirao@gmail.com
License: MIT
Keywords: backend rest web service
Platform: UNKNOWN
Classifier: Development Status :: 3 - Alpha
Classifier: Intended Audience :: Developers
Classifier: Topic :: Software Development :: Libraries :: Application Frameworks
Classifier: License :: OSI Approved :: MIT License
Classifier: Programming Language :: Python :: 2
Classifier: Programming Language :: Python :: 2.6
Classifier: Programming Language :: Python :: 2.7
Requires-Dist: Twisted
Requires-Dist: cyclone
Requires-Dist: service-identity
